{"GlobalPropertiesHash":"BIWH3tyNMivIgPB0s53QeAYc4Bv61Q4SkYx7Mu5DxPE=","FingerprintPatternsHash":"gq3WsqcKBUGTSNle7RKKyXRIwh7M8ccEqOqYvIzoM04=","PropertyOverridesHash":"8ZRc1sGeVrPBx4lD717BgRaQekyh78QKV9SKsdt638U=","InputHashes":["VW7a0S/6gbhXKhWaINZZtYD8otYR2AfQ09BeuhK4aZw=","ff\u002BtBNJ4pToce/QIsh\u002BXyQA\u002BvTRqGX8idvkYWEEOszM=","qekXJVBXLh3b4ccXVuN0HDiyE5J9v0LcR0zeyVp\u002BIFw=","52O4Wnpy/BHpPrUg8zOq8swjlXTGNiYjT8X32q4X4Qw=","zagwRS9Fg290itUDKjPyB85zjG3T5B\u002B8ZbumHafMwJU=","\u002Bx58kU7cScpXBnpFKaWrKkDn/uFpX\u002Bw8s/74W7ud/lE="],"CachedAssets":{"VW7a0S/6gbhXKhWaINZZtYD8otYR2AfQ09BeuhK4aZw=":{"Identity":"C:\\Users\\mdit22\\Documents\\GitHub\\Demo2\\Demo2\\wwwroot\\index.html","SourceId":"EmployeeApi","SourceType":"Discovered","ContentRoot":"C:\\Users\\mdit22\\Documents\\GitHub\\Demo2\\Demo2\\wwwroot\\","BasePath":"_content/EmployeeApi","RelativePath":"index#[.{fingerprint}]?.html","AssetKind":"All","AssetMode":"All","AssetRole":"Primary","AssetMergeBehavior":null,"AssetMergeSource":"","RelatedAsset":null,"AssetTraitName":null,"AssetTraitValue":null,"Fingerprint":"r9aur5lrsf","Integrity":"gTGMsnMaUgrx23zhFX3YBfRXIdB4BA7OJmtUrWEcdsI=","CopyToOutputDirectory":"Never","CopyToPublishDirectory":"PreserveNewest","OriginalItemSpec":"wwwroot\\index.html","FileLength":4003,"LastWriteTime":"2025-05-30T12:05:14.4647034+00:00"},"ff\u002BtBNJ4pToce/QIsh\u002BXyQA\u002BvTRqGX8idvkYWEEOszM=":{"Identity":"C:\\Users\\mdit22\\Documents\\GitHub\\Demo2\\Demo2\\wwwroot\\index.js","SourceId":"EmployeeApi","SourceType":"Discovered","ContentRoot":"C:\\Users\\mdit22\\Documents\\GitHub\\Demo2\\Demo2\\wwwroot\\","BasePath":"_content/EmployeeApi","RelativePath":"index#[.{fingerprint}]?.js","AssetKind":"All","AssetMode":"All","AssetRole":"Primary","AssetMergeBehavior":null,"AssetMergeSource":"","RelatedAsset":null,"AssetTraitName":null,"AssetTraitValue":null,"Fingerprint":"snc3wy7yux","Integrity":"KMW/BnKROjzpQQ\u002Bx5f0j8dezUCzMtYvId5RzQJihF2A=","CopyToOutputDirectory":"Never","CopyToPublishDirectory":"PreserveNewest","OriginalItemSpec":"wwwroot\\index.js","FileLength":2951,"LastWriteTime":"2025-05-30T12:05:14.4208241+00:00"},"qekXJVBXLh3b4ccXVuN0HDiyE5J9v0LcR0zeyVp\u002BIFw=":{"Identity":"C:\\Users\\mdit22\\Documents\\GitHub\\Demo2\\Demo2\\wwwroot\\style.css","SourceId":"EmployeeApi","SourceType":"Discovered","ContentRoot":"C:\\Users\\mdit22\\Documents\\GitHub\\Demo2\\Demo2\\wwwroot\\","BasePath":"_content/EmployeeApi","RelativePath":"style#[.{fingerprint}]?.css","AssetKind":"All","AssetMode":"All","AssetRole":"Primary","AssetMergeBehavior":null,"AssetMergeSource":"","RelatedAsset":null,"AssetTraitName":null,"AssetTraitValue":null,"Fingerprint":"c1dkeum4r4","Integrity":"ABu8KTAEOGycP/CeYYDtzCDjE4NhGY/fNdHnDg1SgKI=","CopyToOutputDirectory":"Never","CopyToPublishDirectory":"PreserveNewest","OriginalItemSpec":"wwwroot\\style.css","FileLength":637,"LastWriteTime":"2025-05-29T11:45:14+00:00"}},"CachedCopyCandidates":{}}